drf_webhooks/LICENSE
drf_webhooks/__init__.py
drf_webhooks/admin.py
drf_webhooks/api.py
drf_webhooks/apps.py
drf_webhooks/config.py
drf_webhooks/fields.py
drf_webhooks/main.py
drf_webhooks/middleware.py
drf_webhooks/models.py
drf_webhooks/serializers.py
drf_webhooks/sessions.py
drf_webhooks/tasks.py
drf_webhooks/tests/__init__.py
drf_webhooks/tests/apps.py
drf_webhooks/tests/migrations/0001_initial.py
drf_webhooks/tests/migrations/__init__.py
drf_webhooks/tests/models.py
drf_webhooks/tests/serializers.py
drf_webhooks/tests/test_utils.py
drf_webhooks/tests/test_webhooks.py
drf_webhooks/utils.py
drf_webhooks-0.2.0.dist-info/LICENSE
drf_webhooks-0.2.0.dist-info/WHEEL
drf_webhooks-0.2.0.dist-info/METADATA
drf_webhooks-0.2.0.dist-info/RECORD
