Metadata-Version: 2.1
Name: drf-webhooks
Version: 0.2.0
Summary: Setup webhooks using existing DRF Serializers
Home-page: https://github.com/demux/drf-webhooks
License: MIT
Keywords: django,drf,rest,djangorestapi,webhooks
Author: Arnar Yngvason
Author-email: arnar@reon.is
Requires-Python: >=3.10,<4.0
Classifier: License :: OSI Approved :: MIT License
Classifier: Programming Language :: Python :: 3
Classifier: Programming Language :: Python :: 3.10
Classifier: Programming Language :: Python :: 3.11
Requires-Dist: Django (>=4.1,<5.0)
Requires-Dist: celery (>=5.2,<6.0)
Requires-Dist: djangorestframework (>=3.14,<4.0)
Requires-Dist: djangorestframework-xml (>=2.0,<3.0)
Requires-Dist: httpx (>=0.23,<0.24)
Requires-Dist: inflection (>=0.5,<0.6)
Requires-Dist: pendulum (>=2.1,<3.0)
Requires-Dist: pytimeparse (>=1.1,<2.0)
Requires-Dist: xmltodict (>=0.13,<0.14)
Project-URL: Repository, https://github.com/demux/drf-webhooks
